yoneq_text2sql/__init__.py
yoneq_text2sql/local.py
yoneq_text2sql/utils.py
yoneq_text2sql/ZhipuAI/ZhipuAI_Chat.py
yoneq_text2sql/ZhipuAI/ZhipuAI_embeddings.py
yoneq_text2sql/ZhipuAI/__init__.py
yoneq_text2sql/anthropic/__init__.py
yoneq_text2sql/anthropic/anthropic_chat.py
yoneq_text2sql/azuresearch/__init__.py
yoneq_text2sql/azuresearch/azuresearch_vector.py
yoneq_text2sql/base/__init__.py
yoneq_text2sql/base/base.py
yoneq_text2sql/bedrock/__init__.py
yoneq_text2sql/bedrock/bedrock_converse.py
yoneq_text2sql/chromadb/__init__.py
yoneq_text2sql/chromadb/chromadb_vector.py
yoneq_text2sql/exceptions/__init__.py
yoneq_text2sql/faiss/__init__.py
yoneq_text2sql/faiss/faiss.py
yoneq_text2sql/google/__init__.py
yoneq_text2sql/google/bigquery_vector.py
yoneq_text2sql/google/gemini_chat.py
yoneq_text2sql/hf/__init__.py
yoneq_text2sql/hf/hf.py
yoneq_text2sql/marqo/__init__.py
yoneq_text2sql/marqo/marqo.py
yoneq_text2sql/milvus/__init__.py
yoneq_text2sql/milvus/milvus_vector.py
yoneq_text2sql/mistral/__init__.py
yoneq_text2sql/mistral/mistral.py
yoneq_text2sql/mock/__init__.py
yoneq_text2sql/mock/embedding.py
yoneq_text2sql/mock/llm.py
yoneq_text2sql/mock/vectordb.py
yoneq_text2sql/ollama/__init__.py
yoneq_text2sql/ollama/ollama.py
yoneq_text2sql/openai/__init__.py
yoneq_text2sql/openai/openai_chat.py
yoneq_text2sql/openai/openai_embeddings.py
yoneq_text2sql/opensearch/__init__.py
yoneq_text2sql/opensearch/opensearch_vector.py
yoneq_text2sql/pgvector/__init__.py
yoneq_text2sql/pgvector/pgvector.py
yoneq_text2sql/pinecone/__init__.py
yoneq_text2sql/pinecone/pinecone_vector.py
yoneq_text2sql/qdrant/__init__.py
yoneq_text2sql/qdrant/qdrant.py
yoneq_text2sql/qianfan/Qianfan_Chat.py
yoneq_text2sql/qianfan/Qianfan_embeddings.py
yoneq_text2sql/qianfan/__init__.py
yoneq_text2sql/qianwen/QianwenAI_chat.py
yoneq_text2sql/qianwen/QianwenAI_embeddings.py
yoneq_text2sql/qianwen/__init__.py
yoneq_text2sql/types/__init__.py
yoneq_text2sql/vllm/__init__.py
yoneq_text2sql/vllm/vllm.py
yoneq_text2sql-0.1.1.dist-info/LICENSE
yoneq_text2sql-0.1.1.dist-info/WHEEL
yoneq_text2sql-0.1.1.dist-info/METADATA
yoneq_text2sql-0.1.1.dist-info/RECORD
